Metadata-Version: 2.1
Name: streamlit-wordcloud-updated
Version: 0.1.1
Summary: This is an interactive Wordcloud component for Streamlit. This is based on React-Wordcloud (https://github.com/chrisrzhou/react-wordcloud).
Home-page: https://github.com/rezaho/streamlit-wordcloud
Author: Gene Ruebsamen
Author-email: ruebsamen.gene@gmail.com
License: UNKNOWN
Platform: UNKNOWN
Requires-Python: >=3.6
License-File: LICENSE
Requires-Dist: matplotlib (==3.7.1)
Requires-Dist: numpy (==1.24.3)
Requires-Dist: streamlit (>=0.63)
